{
  "id": "ayuda",
  "title": "Ayuda",
  "description": "No veo mensajes",
  "source": "@site/docs/ayuda.md",
  "sourceDirName": ".",
  "slug": "/ayuda",
  "permalink": "/mi-primer-nodo-iot-ambiental/actividades/ayuda",
  "draft": false,
  "unlisted": false,
  "tags": [],
  "version": "current",
  "frontMatter": {
    "title": "Ayuda"
  },
  "sidebar": "tutorialSidebar",
  "previous": {
    "title": "6. Medir partículas",
    "permalink": "/mi-primer-nodo-iot-ambiental/actividades/medir-particulas"
  }
}